pymindlabs/__init__.py
pymindlabs/prox.py
pymindlabs/transform.py
pymindlabs/util.py
pymindlabs-1.0.1.dist-info/licenses/LICENSE
pymindlabs-1.0.1.dist-info/METADATA
pymindlabs-1.0.1.dist-info/WHEEL
pymindlabs-1.0.1.dist-info/top_level.txt
pymindlabs-1.0.1.dist-info/RECORD
