Metadata-Version: 2.4
Name: pymindlabs
Version: 1.0.1
Summary: Python implementation of Multiscale Nemirovski Dantzig Estimators
Home-page: https://github.com/housenli/pyMIND
Author: {'Leo Claus Weber', 'Housen Li'}
License-File: LICENSE
Requires-Dist: imageio>=2.9.0
Requires-Dist: matplotlib>=3.4.2
Requires-Dist: numpy>=1.21.0
Requires-Dist: scipy>=1.6.3
Requires-Dist: PyWavelets>=1.3.0
Requires-Dist: numba>=0.55.1
Requires-Dist: pyshearlab-mind>=0.0.2
Dynamic: author
Dynamic: home-page
Dynamic: license-file
Dynamic: requires-dist
Dynamic: summary
